azure/__init__.py
azure/cli/__init__.py
azure/cli/command_modules/__init__.py
azure/cli/command_modules/dls/__init__.py
azure/cli/command_modules/dls/_client_factory.py
azure/cli/command_modules/dls/_help.py
azure/cli/command_modules/dls/_params.py
azure/cli/command_modules/dls/_validators.py
azure/cli/command_modules/dls/commands.py
azure/cli/command_modules/dls/custom.py
azure_cli_dls-0.1.10.dist-info/METADATA
azure_cli_dls-0.1.10.dist-info/WHEEL
azure_cli_dls-0.1.10.dist-info/top_level.txt
azure_cli_dls-0.1.10.dist-info/RECORD
